Workbook

Sheet DASHBOARD
A1: COMPANY | B1: REVENUE | C1: NET PROFIT | D1: ASSETS | E1: OTHER LIABILITIES | F1: PROFIT MARGIN | G1: DEBT RATIO | I1: HIGHEST REVENUE | J1: HIGHEST PROFIT | K1: AVERAGE PROFIT MARGIN | L1: Lowest Debt Ratio | M1: EQUITY | N1: ROE | O1: ROA | P1: HIGEST ROE | Q1: HIGHEST ROA | R1: Metric | S1: Best Company | T1: Value
A2: Sun Pharma | B2: 52578 | C2: 10965 | D2: 91908 | E2: 19960 | F2: =C2/B2 -> 0.2085473 | G2: =E2/D2 -> 0.2171737 | I2: =MAX(B2:B6) -> 52578 | J2: =MAX(C2:C6) -> 10965 | K2: =AVERAGE(F2:F6) -> 0.15885993 | L2: =MIN(G2:G6) -> 0.15272942 | M2: 72218 | N2: =C2/M2 -> 0.15183195 | O2: =C2/D2 -> 0.11930409 | P2: =MAX(N2:N6) -> 0.19217578 | Q2: =MAX(O2:O6) -> 0.11930409 | R2: Current Ratio | S2: =INDEX(CALCULATIONS!A3:A7,MATCH(MAX(CALCULATIONS!B3:B7),CALCULATIONS!B3:B7,0)) -> Aurobindo Pharma | T2: =MAX(CALCULATIONS!B3:B7) -> 3.4480504
A3: Dr Reddy's | B3: 32644 | C3: 5725 | D3: 48023 | E3: 9797 | F3: =C3/B3 -> 0.17537679 | G3: =E3/D3 -> 0.20400641 | M3: 33549 | N3: =C3/M3 -> 0.17064592 | O3: =C3/D3 -> 0.11921371 | R3: Quick Ratio | S3: =INDEX(CALCULATIONS!A3:A7,MATCH(MAX(CALCULATIONS!K3:K7),CALCULATIONS!K3:K7,0)) -> Aurobindo Pharma | T3: =MAX(CALCULATIONS!K3:K7) -> 2.2171375
A4: Cipla | B4: 27548 | C4: 4269 | D4: 37334 | E4: 5702 | F4: =C4/B4 -> 0.15496588 | G4: =E4/D4 -> 0.15272942 | M4: 31194 | N4: =C4/M4 -> 0.13685324 | O4: =C4/D4 -> 0.11434617 | R4: ROCE | S4: =INDEX(CALCULATIONS!A3:A7,MATCH(MAX(CALCULATIONS!J3:J7),CALCULATIONS!J3:J7,0)) -> Lupin | T4: =MAX(CALCULATIONS!J3:J7) -> 0.233
A5: Lupin | B5: 22708 | C5: 3306 | D5: 28978 | E5: 6327 | F5: =C5/B5 -> 0.14558746 | G5: =E5/D5 -> 0.21833805 | M5: 17203 | N5: =C5/M5 -> 0.19217578 | O5: =C5/D5 -> 0.11408655 | R5: Fixed Asset Turnover | S5: =INDEX(CALCULATIONS!A3:A7,MATCH(MAX(CALCULATIONS!S3:S7),CALCULATIONS!S3:S7,0)) -> Cipla | T5: =MAX(CALCULATIONS!S3:S7) -> 2.7531481
A6: Aurobindo Pharma | B6: 31724 | C6: 3484 | D6: 49482 | E6: 8566 | F6: =C6/B6 -> 0.10982222 | G6: =E6/D6 -> 0.17311346 | M6: 32653 | N6: =C6/M6 -> 0.1066977 | O6: =C6/D6 -> 0.070409442
H32: Key Findings
E34: 1. Sun Pharma recorded the highest Revenue (₹52,578 Cr), making it the largest company among the selected pharmaceutical companies.
E36: 2. Sun Pharma generated the highest Net Profit (₹10,965 Cr), indicating strong profitability.
E38: 3. Sun Pharma achieved the highest Gross Profit Margin (34.08%), reflecting effective cost management.
E40: 4. Lupin recorded the highest ROCE (23.30%), indicating the most efficient utilization of capital employed.
E42: 5. Aurobindo Pharma reported the highest Current Ratio (3.45), demonstrating the strongest short-term liquidity.
E44: 6. Aurobindo Pharma achieved the highest Quick Ratio (2.20), showing excellent ability to meet short-term obligations without relying on inventory.
E46: 7. Sun Pharma recorded the highest Cash Ratio (0.65), reflecting the strongest immediate liquidity position.
E48: 8. Cipla achieved the highest Fixed Asset Turnover (2.75), indicating the most efficient utilization of fixed assets.

Sheet Financial Data
A2: Company | B2: Year | C2: Revenue | D2: COGS | E2: Gross Profit | F2: EBIT | G2: EBITDA | H2: Net Profit | I2: Current Assets | J2: Inventory | K2: Cash | L2: Current Liabilities | M2: Total Assets | N2: Net Fixed Assets | O2: Total Debt | P2: Shareholders' Equity | Q2: Interest Expense | R2: Credit Sales | S2: Trade Receivables | T2: Credit Purchases | U2: Trade Payables | V2: Outstanding Shares | W2: Market Price/Share | X2: Dividend/Share | Y2: Depreciation
A3: SUN PHARMA | B3: 2025 | C3: 52578 | D3: 34658 | E3: =C3-D3 -> 17920 | F3: 15114 | G3: =F3+Y3 -> 17689 | H3: 10965 | I3: 44324 | J3: 10243 | K3: 11332 | L3: 17328 | M3: 91908 | N3: 22586 | O3: 2362 | P3: 72218 | Q3: 231 | R3: 52578 | S3: 13046 | U3: 6184 | V3: 239.93 | W3: 1914 | Y3: 2575
A4: DR.REDDY'S | B4: 2025 | C4: 32644 | D4: 22110 | E4: =C4-D4 -> 10534 | F4: 8547 | G4: =F4+Y4 -> 10251 | H4: 5725 | I4: 23280 | J4: 7108 | K4: 2460 | L4: 9797 | M4: 48023 | N4: 18226 | O4: 4677 | P4: 33549 | Q4: 283 | R4: 32644 | S4: 9042 | U4: 2648 | V4: 83.46 | W4: 1370 | Y4: 1704
A5: CIPLA | B5: 2025 | C5: 27548 | D5: 19281 | E5: =C5-D5 -> 8267 | F5: 7128 | G5: =F5+Y5 -> 8235 | H5: 4269 | I5: 17828 | J5: 5642 | K5: 800 | L5: 5702 | M5: 37334 | N5: 10006 | O5: 438 | P5: 31194 | Q5: 62 | R5: 27548 | S5: 5506 | U5: 2837 | V5: 80.77 | W5: 1459 | Y5: 1107
A6: LUPIN | B6: 2025 | C6: 22708 | D6: 15966 | E6: =C6-D6 -> 6742 | F6: 5278 | G6: =F6+Y6 -> 6447 | H6: 3306 | I6: 17596 | J6: 5476 | K6: 3142 | L6: 6327 | M6: 28978 | N6: 9719 | O6: 5448 | P6: 17203 | Q6: 295 | R6: 22708 | S6: 5497 | U6: 2958 | V6: 45.7 | W6: 2462 | Y6: 1169
A7: Aurobindo Pharma | B7: 2025 | C7: 31724 | D7: 23067 | E7: =C7-D7 -> 8657 | F7: 6551 | G7: =F7+Y7 -> 8200 | H7: 3484 | I7: 29536 | J7: 10544 | K7: 8235 | L7: 8566 | M7: 49482 | N7: 14794 | O7: 8263 | P7: 32653 | Q7: 457 | R7: 31724 | S7: 5746 | U7: 4187 | V7: 58.06 | W7: 1622 | Y7: 1649

Sheet CALCULATIONS
A1: A | B1: B | C1: C | D1: D | E1: E | F1: F | G1: G | H1: H | I1: I | J1: J | K1: K | L1: L | M1: M | N1: N | O1: O | P1: P | Q1: Q | R1: R | S1: S
A2: Company | B2: Current Ratio | C2: Debt-to-Equity | D2: Interest Coverage | E2: Asset Turnover | F2: Status | G2: Gross Profit Margin | H2: Operating Margin | I2: EBITDA Margin | J2: ROCE | K2: Quick Ratio | L2: Cash Ratio | M2: Inventory turnover | N2: Receivable turnover | O2: Working capital | P2: Working capital turnover | Q2: Equity ratio | R2: debt ratio | S2: fixed asset turnover
A3: Sun Pharma | B3: ='Financial Data'!I3/'Financial Data'!L3 -> 2.5579409 | C3: ='Financial Data'!O3/'Financial Data'!P3 -> 0.032706527 | D3: ='Financial Data'!F3/'Financial Data'!Q3 -> 65.428571 | E3: ='Financial Data'!C3/'Financial Data'!M3 -> 0.57207207 | G3: ='Financial Data'!E3/'Financial Data'!C3*100 -> 34.082696 | H3: ='Financial Data'!F3/'Financial Data'!C3*100 -> 28.745863 | I3: ='Financial Data'!G3/'Financial Data'!C3*100 -> 33.643349 | J3: 0.2026 | K3: =('Financial Data'!I3-'Financial Data'!J3)/'Financial Data'!L3 -> 1.9668167 | L3: ='Financial Data'!K3/'Financial Data'!L3 -> 0.65397045 | M3: ='Financial Data'!D3/'Financial Data'!J3 -> 3.383579 | N3: ='Financial Data'!R3/'Financial Data'!S3 -> 4.0302008 | O3: ='Financial Data'!I3-'Financial Data'!L3 -> 26996 | P3: ='Financial Data'!C3/CALCULATIONS!O3 -> 1.9476219 | Q3: ='Financial Data'!P3/'Financial Data'!M3 -> 0.78576402 | R3: ='Financial Data'!O3/'Financial Data'!M3 -> 0.025699613 | S3: ='Financial Data'!C3/'Financial Data'!N3 -> 2.3279022
A4: Dr. Reddy's | B4: ='Financial Data'!I4/'Financial Data'!L4 -> 2.3762376 | C4: ='Financial Data'!O4/'Financial Data'!P4 -> 0.13940803 | D4: ='Financial Data'!F4/'Financial Data'!Q4 -> 30.201413 | E4: ='Financial Data'!C4/'Financial Data'!M4 -> 0.67975762 | G4: ='Financial Data'!E4/'Financial Data'!C4*100 -> 32.26933 | H4: ='Financial Data'!F4/'Financial Data'!C4*100 -> 26.182453 | I4: ='Financial Data'!G4/'Financial Data'!C4*100 -> 31.402402 | J4: 0.2236 | K4: =('Financial Data'!I4-'Financial Data'!J4)/'Financial Data'!L4 -> 1.6507094 | L4: ='Financial Data'!K4/'Financial Data'!L4 -> 0.25109727 | M4: ='Financial Data'!D4/'Financial Data'!J4 -> 3.1105796 | N4: ='Financial Data'!R4/'Financial Data'!S4 -> 3.6102632 | O4: ='Financial Data'!I4-'Financial Data'!L4 -> 13483 | P4: ='Financial Data'!C4/CALCULATIONS!O4 -> 2.4211229 | Q4: ='Financial Data'!P4/'Financial Data'!M4 -> 0.69860275 | R4: ='Financial Data'!O4/'Financial Data'!M4 -> 0.097390834 | S4: ='Financial Data'!C4/'Financial Data'!N4 -> 1.7910677
A5: Cipla | B5: ='Financial Data'!I5/'Financial Data'!L5 -> 3.1266222 | C5: ='Financial Data'!O5/'Financial Data'!P5 -> 0.014041162 | D5: ='Financial Data'!F5/'Financial Data'!Q5 -> 114.96774 | E5: ='Financial Data'!C5/'Financial Data'!M5 -> 0.73787968 | G5: ='Financial Data'!E5/'Financial Data'!C5*100 -> 30.009438 | H5: ='Financial Data'!F5/'Financial Data'!C5*100 -> 25.874837 | I5: ='Financial Data'!G5/'Financial Data'!C5*100 -> 29.893277 | J5: 0.2253 | K5: =('Financial Data'!I5-'Financial Data'!J5)/'Financial Data'!L5 -> 2.1371449 | L5: ='Financial Data'!K5/'Financial Data'!L5 -> 0.14030165 | M5: ='Financial Data'!D5/'Financial Data'!J5 -> 3.4174052 | N5: ='Financial Data'!R5/'Financial Data'!S5 -> 5.0032692 | O5: ='Financial Data'!I5-'Financial Data'!L5 -> 12126 | P5: ='Financial Data'!C5/CALCULATIONS!O5 -> 2.2718126 | Q5: ='Financial Data'!P5/'Financial Data'!M5 -> 0.83553865 | R5: ='Financial Data'!O5/'Financial Data'!M5 -> 0.011731933 | S5: ='Financial Data'!C5/'Financial Data'!N5 -> 2.7531481
A6: Lupin | B6: ='Financial Data'!I6/'Financial Data'!L6 -> 2.7810969 | C6: ='Financial Data'!O6/'Financial Data'!P6 -> 0.31668895 | D6: ='Financial Data'!F6/'Financial Data'!Q6 -> 17.891525 | E6: ='Financial Data'!C6/'Financial Data'!M6 -> 0.78362896 | G6: ='Financial Data'!E6/'Financial Data'!C6*100 -> 29.689977 | H6: ='Financial Data'!F6/'Financial Data'!C6*100 -> 23.24291 | I6: ='Financial Data'!G6/'Financial Data'!C6*100 -> 28.390875 | J6: 0.233 | K6: =('Financial Data'!I6-'Financial Data'!J6)/'Financial Data'!L6 -> 1.9155998 | L6: ='Financial Data'!K6/'Financial Data'!L6 -> 0.49660187 | M6: ='Financial Data'!D6/'Financial Data'!J6 -> 2.9156318 | N6: ='Financial Data'!R6/'Financial Data'!S6 -> 4.1309805 | O6: ='Financial Data'!I6-'Financial Data'!L6 -> 11269 | P6: ='Financial Data'!C6/CALCULATIONS!O6 -> 2.0150856 | Q6: ='Financial Data'!P6/'Financial Data'!M6 -> 0.59365726 | R6: ='Financial Data'!O6/'Financial Data'!M6 -> 0.18800469 | S6: ='Financial Data'!C6/'Financial Data'!N6 -> 2.3364544
A7: Aurobindo Pharma | B7: ='Financial Data'!I7/'Financial Data'!L7 -> 3.4480504 | C7: ='Financial Data'!O7/'Financial Data'!P7 -> 0.25305485 | D7: ='Financial Data'!F7/'Financial Data'!Q7 -> 14.334792 | E7: ='Financial Data'!C7/'Financial Data'!M7 -> 0.64112202 | G7: ='Financial Data'!E7/'Financial Data'!C7*100 -> 27.288488 | H7: ='Financial Data'!F7/'Financial Data'!C7*100 -> 20.649981 | I7: ='Financial Data'!G7/'Financial Data'!C7*100 -> 25.847938 | J7: 0.1601 | K7: =('Financial Data'!I7-'Financial Data'!J7)/'Financial Data'!L7 -> 2.2171375 | L7: ='Financial Data'!K7/'Financial Data'!L7 -> 0.96135886 | M7: ='Financial Data'!D7/'Financial Data'!J7 -> 2.1876897 | N7: ='Financial Data'!R7/'Financial Data'!S7 -> 5.5210581 | O7: ='Financial Data'!I7-'Financial Data'!L7 -> 20970 | P7: ='Financial Data'!C7/CALCULATIONS!O7 -> 1.5128278 | Q7: ='Financial Data'!P7/'Financial Data'!M7 -> 0.65989653 | R7: ='Financial Data'!O7/'Financial Data'!M7 -> 0.16699002 | S7: ='Financial Data'!C7/'Financial Data'!N7 -> 2.1443829
